core/Environment.py
core/Model.py
core/Schedule.py
core/Steppables.py
core/__init__.py
examples/ExampleWithEnvironment.py
examples/GameOfLifeExample.py
examples/ParticleSwarmOptimizationExample.py
examples/TrivialExample.py
examples/__init__.py
panaxea/__init__.py
panaxea/core/Environment.py
panaxea/core/Model.py
panaxea/core/Schedule.py
panaxea/core/Steppables.py
panaxea/core/__init__.py
panaxea/toolkit/Toolkit.py
panaxea/toolkit/__init__.py
tests/__init__.py
tests/test_environment.py
tests/test_model.py
tests/test_schedule.py
tests/test_steppables.py
tests/test_toolkit.py
tests/resources/SampleSteppables.py
tests/resources/__init__.py
toolkit/Toolkit.py
toolkit/__init__.py
PanaXea-0.11.0.dev1.dist-info/AUTHORS.md
PanaXea-0.11.0.dev1.dist-info/LICENSE.md
PanaXea-0.11.0.dev1.dist-info/METADATA
PanaXea-0.11.0.dev1.dist-info/WHEEL
PanaXea-0.11.0.dev1.dist-info/top_level.txt
PanaXea-0.11.0.dev1.dist-info/RECORD
