Metadata-Version: 2.1
Name: PanaXea
Version: 0.11.0.dev1
Summary: A minimalist framework for agent-based modelling in Python.
Home-page: https://https://github.com/DarioPanada/panaxea
Author: Dario Panada
Author-email: dario.panada@manchester.ac.uk
License: UNKNOWN
Platform: UNKNOWN
Classifier: Programming Language :: Python :: 2.7
Classifier: License :: OSI Approved :: MIT License
Classifier: Operating System :: OS Independent
Requires-Python: >=2.7
